Metadata-Version: 2.4
Name: certbot_dns_mchost24
Version: 1.0.0
Summary: Certbot DNS Authenticator plugin for MCHost24
Author-email: JoeJoeTV <joejoetv@joejoetv.de>
License-Expression: GPL-3.0
Project-URL: Homepage, https://github.com/JoeJoeTV/certbot-dns-mchost24
Project-URL: Issues, https://github.com/JoeJoeTV/certbot-dns-mchost24/issues
Classifier: Development Status :: 1 - Planning
Classifier: Environment :: Plugins
Classifier: Intended Audience :: System Administrators
Classifier: Operating System :: POSIX :: Linux
Classifier: Programming Language :: Python
Classifier: Programming Language :: Python :: 3
Classifier: Topic :: Internet :: Name Service (DNS)
Classifier: Topic :: Internet :: WWW/HTTP
Classifier: Topic :: Security
Classifier: Topic :: Security :: Cryptography
Classifier: Topic :: System :: Networking
Classifier: Topic :: System :: Systems Administration
Classifier: Topic :: Utilities
Requires-Python: !=3.0.*,!=3.1.*,!=3.2.*,!=3.3.*,>=2.7
License-File: LICENSE
Requires-Dist: acme>=2.9.0
Requires-Dist: certbot>=2.9.0
Requires-Dist: setuptools
Requires-Dist: mchost24
Dynamic: license-file
